{
  "clip_path": "/Volumes/drev-ventura/video-repos/videoai/clips/Dark Elf.mp4",
  "frames": [
    {
      "clip_path": "/Volumes/drev-ventura/video-repos/videoai/clips/Dark Elf.mp4",
      "frame_path": "/Volumes/drev-ventura/video-repos/videoai/frames/clips/Dark Elf/frame_000_0.00s.jpg",
      "timestamp": 0.0,
      "caption": "A mysterious figure with glowing blue eyes stands in a dimly lit forest, wearing a hood with wolf-like ears. The character's intense gaze and intricate facial markings add to the enigmatic atmosphere.",
      "description": "The scene is set in a shadowy forest, where a character with striking blue eyes and a wolf-themed hood stands prominently. The setting suggests a mystical or fantasy theme, with the character exuding an aura of mystery and intrigue.",
      "labels": {
        "people": [
          "character"
        ],
        "nature": [
          "forest"
        ],
        "objects": [
          "hood",
          "wolf ears"
        ],
        "emotions": [
          "mysterious",
          "intense"
        ],
        "scenes": [
          "fantasy",
          "mystical"
        ],
        "concepts": [
          "mystery",
          "intrigue"
        ]
      },
      "metadata": {},
      "confidence": 0.9
    },
    {
      "clip_path": "/Volumes/drev-ventura/video-repos/videoai/clips/Dark Elf.mp4",
      "frame_path": "/Volumes/drev-ventura/video-repos/videoai/frames/clips/Dark Elf/frame_001_4.00s.jpg",
      "timestamp": 4.0,
      "caption": "A mysterious figure with glowing blue eyes stares intently forward, framed by a dark, fur-like hood. Intricate facial markings and a choker necklace add to the enigmatic aura.",
      "description": "The scene depicts a close-up of a character with striking blue eyes and dark hair, wearing a hood that resembles animal fur. The setting is dark and atmospheric, enhancing the mystical and intense presence of the figure.",
      "labels": {
        "people": [
          "character",
          "face"
        ],
        "objects": [
          "hood",
          "choker necklace"
        ],
        "emotions": [
          "intensity",
          "mystery"
        ],
        "scenes": [
          "close-up",
          "dark"
        ],
        "concepts": [
          "mystical",
          "enigmatic"
        ]
      },
      "metadata": {},
      "confidence": 0.9
    }
  ],
  "summary": "People: character, face. Nature: forest. Objects: hood, wolf ears, choker necklace. Emotions: mysterious, intense, intensity, mystery. Scenes: fantasy, mystical, close-up, dark. Concepts: mystery, intrigue, mystical, enigmatic",
  "primary_labels": {
    "people": [
      "character",
      "face"
    ],
    "nature": [
      "forest"
    ],
    "objects": [
      "hood",
      "wolf ears",
      "choker necklace"
    ],
    "emotions": [
      "mysterious",
      "intense",
      "intensity",
      "mystery"
    ],
    "scenes": [
      "fantasy",
      "mystical",
      "close-up",
      "dark"
    ],
    "concepts": [
      "mystery",
      "intrigue",
      "mystical",
      "enigmatic"
    ]
  },
  "metadata": {}
}