{
  "clip_path": "/Volumes/drev-ventura/video-repos/videoai/clips/not_filtered/a daydream.mp4",
  "frames": [
    {
      "clip_path": "/Volumes/drev-ventura/video-repos/videoai/clips/not_filtered/a daydream.mp4",
      "frame_path": "/Volumes/drev-ventura/video-repos/videoai/frames/clips/not_filtered/a daydream/frame_000_0.00s.jpg",
      "timestamp": 0.0,
      "caption": "A solitary figure sits atop a large cloud, silhouetted against a vast sky. The scene conveys a sense of tranquility and introspection, with the sun casting a gentle light over the cloudscape.",
      "description": "The image depicts a serene and surreal setting where a person is seated on a cloud high above the earth. The expansive sky and soft lighting create a peaceful and contemplative atmosphere.",
      "labels": {
        "people": [
          "silhouette"
        ],
        "nature": [
          "cloud",
          "sky"
        ],
        "objects": [],
        "actions": [
          "sitting"
        ],
        "emotions": [
          "tranquility",
          "introspection"
        ],
        "scenes": [
          "cloudscape",
          "sky"
        ],
        "concepts": [
          "solitude",
          "peace"
        ]
      },
      "metadata": {},
      "confidence": 0.9
    },
    {
      "clip_path": "/Volumes/drev-ventura/video-repos/videoai/clips/not_filtered/a daydream.mp4",
      "frame_path": "/Volumes/drev-ventura/video-repos/videoai/frames/clips/not_filtered/a daydream/frame_001_4.00s.jpg",
      "timestamp": 4.0,
      "caption": "A solitary figure sits atop a large, fluffy cloud, surrounded by a vast expanse of sky. The scene is serene and ethereal, with the sun casting a soft, golden light over the clouds.",
      "description": "The image depicts a tranquil scene where a person is seated on a cloud high above the earth. The setting is otherworldly and peaceful, with a vast sky stretching out in all directions.",
      "labels": {
        "people": [
          "solitary figure"
        ],
        "nature": [
          "cloud",
          "sky"
        ],
        "objects": [],
        "actions": [
          "sitting"
        ],
        "emotions": [
          "serenity",
          "peacefulness"
        ],
        "scenes": [
          "ethereal",
          "tranquil"
        ],
        "concepts": [
          "solitude",
          "meditation"
        ]
      },
      "metadata": {},
      "confidence": 0.9
    },
    {
      "clip_path": "/Volumes/drev-ventura/video-repos/videoai/clips/not_filtered/a daydream.mp4",
      "frame_path": "/Volumes/drev-ventura/video-repos/videoai/frames/clips/not_filtered/a daydream/frame_002_8.00s.jpg",
      "timestamp": 8.0,
      "caption": "A solitary figure sits atop a fluffy cloud, surrounded by a vast expanse of sky. The scene is serene and otherworldly, with soft sunlight illuminating the clouds.",
      "description": "The image depicts a person sitting on a cloud, high above the earth, in a tranquil and dreamlike setting. The sky is vast and open, with gentle sunlight casting a warm glow.",
      "labels": {
        "people": [
          "person"
        ],
        "nature": [
          "cloud",
          "sky"
        ],
        "objects": [],
        "actions": [
          "sitting"
        ],
        "emotions": [
          "serenity",
          "tranquility"
        ],
        "scenes": [
          "aerial",
          "dreamlike"
        ],
        "concepts": [
          "solitude",
          "peace"
        ]
      },
      "metadata": {},
      "confidence": 0.9
    }
  ],
  "summary": "People: silhouette, solitary figure, person. Nature: cloud, sky. Actions: sitting. Emotions: tranquility, serenity, introspection, peacefulness. Scenes: cloudscape, sky, ethereal, tranquil, aerial. Concepts: solitude, peace, meditation",
  "primary_labels": {
    "people": [
      "silhouette",
      "solitary figure",
      "person"
    ],
    "nature": [
      "cloud",
      "sky"
    ],
    "objects": [],
    "actions": [
      "sitting"
    ],
    "emotions": [
      "tranquility",
      "serenity",
      "introspection",
      "peacefulness"
    ],
    "scenes": [
      "cloudscape",
      "sky",
      "ethereal",
      "tranquil",
      "aerial"
    ],
    "concepts": [
      "solitude",
      "peace",
      "meditation"
    ]
  },
  "metadata": {}
}