{
  "clip_path": "/Volumes/drev-ventura/video-repos/videoai/clips/not_filtered/RonaldoWasAnnoyed,AndMessi.mp4",
  "frames": [
    {
      "clip_path": "/Volumes/drev-ventura/video-repos/videoai/clips/not_filtered/RonaldoWasAnnoyed,AndMessi.mp4",
      "frame_path": "/Volumes/drev-ventura/video-repos/videoai/frames/clips/not_filtered/RonaldoWasAnnoyed,AndMessi/frame_000_0.00s.jpg",
      "timestamp": 0.0,
      "caption": "Two men stand in a shallow body of water, one holding a golden trophy. They are wearing soccer jerseys, one in red and green, the other in blue and white stripes.",
      "description": "The scene takes place in a natural setting with a forested background and a calm body of water. Two men are partially submerged, with one holding a trophy and both appearing joyful.",
      "labels": {
        "people": [
          "men"
        ],
        "objects": [
          "trophy",
          "soccer jerseys"
        ],
        "nature": [
          "water",
          "forest"
        ],
        "actions": [
          "standing",
          "holding"
        ],
        "emotions": [
          "joy"
        ],
        "scenes": [
          "outdoor",
          "natural setting"
        ],
        "concepts": [
          "celebration",
          "sports"
        ]
      },
      "metadata": {},
      "confidence": 0.9
    },
    {
      "clip_path": "/Volumes/drev-ventura/video-repos/videoai/clips/not_filtered/RonaldoWasAnnoyed,AndMessi.mp4",
      "frame_path": "/Volumes/drev-ventura/video-repos/videoai/frames/clips/not_filtered/RonaldoWasAnnoyed,AndMessi/frame_001_4.00s.jpg",
      "timestamp": 4.0,
      "caption": "Two individuals stand in a shallow body of water, both wearing soccer jerseys. One person is holding a golden trophy and smiling broadly, while the other looks down with a neutral expression.",
      "description": "The scene takes place in a natural setting with a background of lush greenery. Two people are standing in the water, one holding a trophy, suggesting a celebratory or sports-related context.",
      "labels": {
        "people": [
          "two individuals"
        ],
        "nature": [
          "water",
          "greenery"
        ],
        "objects": [
          "soccer jerseys",
          "trophy"
        ],
        "actions": [
          "standing",
          "holding"
        ],
        "emotions": [
          "happiness",
          "neutral"
        ],
        "scenes": [
          "outdoor",
          "sports"
        ],
        "concepts": [
          "celebration",
          "competition"
        ]
      },
      "metadata": {},
      "confidence": 0.9
    }
  ],
  "summary": "People: men, two individuals. Objects: trophy, soccer jerseys. Nature: water, forest, greenery. Actions: standing, holding. Emotions: joy, happiness, neutral. Scenes: outdoor, natural setting, sports. Concepts: celebration, sports, competition",
  "primary_labels": {
    "people": [
      "men",
      "two individuals"
    ],
    "objects": [
      "trophy",
      "soccer jerseys"
    ],
    "nature": [
      "water",
      "forest",
      "greenery"
    ],
    "actions": [
      "standing",
      "holding"
    ],
    "emotions": [
      "joy",
      "happiness",
      "neutral"
    ],
    "scenes": [
      "outdoor",
      "natural setting",
      "sports"
    ],
    "concepts": [
      "celebration",
      "sports",
      "competition"
    ]
  },
  "metadata": {}
}