{
  "clip_path": "/Volumes/drev-ventura/video-repos/videoai/clips/not_filtered/Mercury Dance: A Family in Motio.mp4",
  "frames": [
    {
      "clip_path": "/Volumes/drev-ventura/video-repos/videoai/clips/not_filtered/Mercury Dance: A Family in Motio.mp4",
      "frame_path": "/Volumes/drev-ventura/video-repos/videoai/frames/clips/not_filtered/Mercury Dance: A Family in Motio/frame_000_0.00s.jpg",
      "timestamp": 0.0,
      "caption": "A mesmerizing metallic liquid sculpture rises from a reflective surface, capturing the eye with its fluid and dynamic form. The background is softly blurred, highlighting the intricate details of the liquid's surface and its mirror-like sheen.",
      "description": "The scene depicts a dynamic splash of metallic liquid, possibly mercury, in an indoor setting with soft lighting. The focus is on the liquid's elegant and fluid form as it appears to defy gravity.",
      "labels": {
        "objects": [
          "metallic liquid",
          "splash",
          "reflective surface"
        ],
        "actions": [
          "rising",
          "splashing"
        ],
        "emotions": [
          "mesmerizing",
          "intriguing"
        ],
        "scenes": [
          "indoor",
          "artistic"
        ],
        "concepts": [
          "fluidity",
          "dynamics"
        ]
      },
      "metadata": {},
      "confidence": 0.9
    },
    {
      "clip_path": "/Volumes/drev-ventura/video-repos/videoai/clips/not_filtered/Mercury Dance: A Family in Motio.mp4",
      "frame_path": "/Volumes/drev-ventura/video-repos/videoai/frames/clips/not_filtered/Mercury Dance: A Family in Motio/frame_001_4.00s.jpg",
      "timestamp": 4.0,
      "caption": "A dynamic splash of liquid metal creates an abstract sculpture-like form, reflecting the ambient light. The scene is set indoors with a blurred background, suggesting a sophisticated environment.",
      "description": "The image captures a moment where liquid metal appears to be frozen mid-splash, forming an intricate, abstract shape. The setting is indoors, possibly a modern or elegant space, with warm lighting in the background.",
      "labels": {
        "objects": [
          "liquid metal",
          "abstract sculpture"
        ],
        "actions": [
          "splash",
          "reflection"
        ],
        "emotions": [
          "intrigue",
          "awe"
        ],
        "scenes": [
          "indoor",
          "modern"
        ],
        "concepts": [
          "fluidity",
          "artistic expression"
        ]
      },
      "metadata": {},
      "confidence": 0.9
    }
  ],
  "summary": "Objects: metallic liquid, splash, reflective surface, liquid metal, abstract sculpture. Actions: rising, splashing, splash, reflection. Emotions: mesmerizing, intriguing, intrigue, awe. Scenes: indoor, artistic, modern. Concepts: fluidity, dynamics, artistic expression",
  "primary_labels": {
    "objects": [
      "metallic liquid",
      "splash",
      "reflective surface",
      "liquid metal",
      "abstract sculpture"
    ],
    "actions": [
      "rising",
      "splashing",
      "splash",
      "reflection"
    ],
    "emotions": [
      "mesmerizing",
      "intriguing",
      "intrigue",
      "awe"
    ],
    "scenes": [
      "indoor",
      "artistic",
      "modern"
    ],
    "concepts": [
      "fluidity",
      "dynamics",
      "artistic expression"
    ]
  },
  "metadata": {}
}