{
  "clip_path": "/Volumes/drev-ventura/video-repos/videoai/clips/not_filtered/Girl And Giant Swan.mp4",
  "frames": [
    {
      "clip_path": "/Volumes/drev-ventura/video-repos/videoai/clips/not_filtered/Girl And Giant Swan.mp4",
      "frame_path": "/Volumes/drev-ventura/video-repos/videoai/frames/clips/not_filtered/Girl And Giant Swan/frame_000_0.00s.jpg",
      "timestamp": 0.0,
      "caption": "A woman in a bikini sits gracefully on the back of a large swan gliding across the ocean. The swan's wings are spread wide, creating an elegant and surreal scene against the backdrop of a sunlit sea.",
      "description": "The image depicts a fantastical scene where a woman is riding a giant swan across the ocean. The setting is serene and dreamlike, with the sun casting a warm glow over the water.",
      "labels": {
        "people": [
          "woman"
        ],
        "animals": [
          "swan"
        ],
        "nature": [
          "ocean",
          "sky"
        ],
        "objects": [],
        "actions": [
          "riding"
        ],
        "emotions": [
          "serenity"
        ],
        "scenes": [
          "fantasy",
          "seascape"
        ],
        "concepts": [
          "surrealism",
          "elegance"
        ]
      },
      "metadata": {},
      "confidence": 0.9
    },
    {
      "clip_path": "/Volumes/drev-ventura/video-repos/videoai/clips/not_filtered/Girl And Giant Swan.mp4",
      "frame_path": "/Volumes/drev-ventura/video-repos/videoai/frames/clips/not_filtered/Girl And Giant Swan/frame_001_4.00s.jpg",
      "timestamp": 4.0,
      "caption": "A woman in a bikini sits gracefully on the back of a giant swan, gliding across a tranquil sea. The swan's wings are spread wide, capturing the sunlight against a backdrop of a clear sky and gentle waves.",
      "description": "The scene depicts a surreal and serene setting where a woman is riding a large swan over a calm ocean. The atmosphere is peaceful and dreamlike, with the sun casting a warm glow over the water.",
      "labels": {
        "people": [
          "woman"
        ],
        "animals": [
          "swan"
        ],
        "nature": [
          "sea",
          "sky",
          "clouds"
        ],
        "objects": [
          "bikini"
        ],
        "actions": [
          "riding",
          "gliding"
        ],
        "emotions": [
          "serene",
          "dreamlike"
        ],
        "scenes": [
          "ocean",
          "fantasy"
        ],
        "concepts": [
          "surrealism",
          "tranquility"
        ]
      },
      "metadata": {},
      "confidence": 0.9
    }
  ],
  "summary": "People: woman. Animals: swan. Nature: sky, ocean, sea, clouds. Objects: bikini. Actions: riding, gliding. Emotions: serenity, serene, dreamlike. Scenes: fantasy, seascape, ocean. Concepts: surrealism, elegance, tranquility",
  "primary_labels": {
    "people": [
      "woman"
    ],
    "animals": [
      "swan"
    ],
    "nature": [
      "sky",
      "ocean",
      "sea",
      "clouds"
    ],
    "objects": [
      "bikini"
    ],
    "actions": [
      "riding",
      "gliding"
    ],
    "emotions": [
      "serenity",
      "serene",
      "dreamlike"
    ],
    "scenes": [
      "fantasy",
      "seascape",
      "ocean"
    ],
    "concepts": [
      "surrealism",
      "elegance",
      "tranquility"
    ]
  },
  "metadata": {}
}