{
  "clip_path": "/Volumes/drev-ventura/video-repos/videoai/clips/not_filtered/PleaseAnimateTheAttachedPhoto.mp4",
  "frames": [
    {
      "clip_path": "/Volumes/drev-ventura/video-repos/videoai/clips/not_filtered/PleaseAnimateTheAttachedPhoto.mp4",
      "frame_path": "/Volumes/drev-ventura/video-repos/videoai/frames/clips/not_filtered/PleaseAnimateTheAttachedPhoto/frame_000_0.00s.jpg",
      "timestamp": 0.0,
      "caption": "A woman in an elegant white and gold gown walks confidently down a cobblestone street, accompanied by a majestic eagle. The scene is set against the backdrop of ancient Roman architecture, including the iconic Colosseum.",
      "description": "The image depicts a blend of modern fashion and ancient Roman elements, creating a surreal and regal atmosphere. The woman, adorned with a golden headpiece, exudes grace and power as she strides alongside the eagle.",
      "labels": {
        "people": [
          "woman"
        ],
        "animals": [
          "eagle"
        ],
        "nature": [],
        "objects": [
          "gown",
          "headpiece"
        ],
        "actions": [
          "walking"
        ],
        "emotions": [
          "confidence"
        ],
        "scenes": [
          "ancient Rome",
          "street"
        ],
        "concepts": [
          "fashion",
          "regality"
        ]
      },
      "metadata": {},
      "confidence": 0.9
    },
    {
      "clip_path": "/Volumes/drev-ventura/video-repos/videoai/clips/not_filtered/PleaseAnimateTheAttachedPhoto.mp4",
      "frame_path": "/Volumes/drev-ventura/video-repos/videoai/frames/clips/not_filtered/PleaseAnimateTheAttachedPhoto/frame_001_4.00s.jpg",
      "timestamp": 4.0,
      "caption": "A woman dressed in an elegant white gown stands confidently on a stone pathway, adorned with a golden crown and accessories. In front of her, a majestic eagle spreads its wings, poised as if ready to take flight. The background features a vast, open landscape under a clear sky.",
      "description": "The scene depicts a regal and mythical setting, with a woman and an eagle positioned prominently in a natural, open environment. The atmosphere suggests a blend of elegance and power, enhanced by the woman's attire and the eagle's presence.",
      "labels": {
        "people": [
          "woman"
        ],
        "animals": [
          "eagle"
        ],
        "nature": [
          "sky",
          "landscape"
        ],
        "objects": [
          "gown",
          "crown",
          "accessories"
        ],
        "actions": [
          "standing",
          "spreading wings"
        ],
        "emotions": [
          "confidence"
        ],
        "scenes": [
          "mythical",
          "regal"
        ],
        "concepts": [
          "elegance",
          "power"
        ]
      },
      "metadata": {},
      "confidence": 0.9
    }
  ],
  "summary": "People: woman. Animals: eagle. Nature: sky, landscape. Objects: gown, headpiece, crown, accessories. Actions: walking, standing, spreading wings. Emotions: confidence. Scenes: ancient Rome, street, mythical, regal. Concepts: fashion, regality, elegance, power",
  "primary_labels": {
    "people": [
      "woman"
    ],
    "animals": [
      "eagle"
    ],
    "nature": [
      "sky",
      "landscape"
    ],
    "objects": [
      "gown",
      "headpiece",
      "crown",
      "accessories"
    ],
    "actions": [
      "walking",
      "standing",
      "spreading wings"
    ],
    "emotions": [
      "confidence"
    ],
    "scenes": [
      "ancient Rome",
      "street",
      "mythical",
      "regal"
    ],
    "concepts": [
      "fashion",
      "regality",
      "elegance",
      "power"
    ]
  },
  "metadata": {}
}